{
  "frontendModules": {
    "@openmrs/esm-primary-navigation-app": "6.0.2",
    "@openmrs/esm-implementer-tools-app": "6.0.2",
    "@openmrs/esm-home-app": "5.5.1",
    "@openmrs/esm-form-builder-app": "2.9.0",
    "@openmrs/esm-form-entry-app": "9.1.1-pre.6560",
    "@openmrs/esm-patient-allergies-app": "9.1.1-pre.6560",
    "@openmrs/esm-patient-conditions-app": "9.1.1-pre.6560",
    "@openmrs/esm-patient-banner-app": "9.1.1-pre.6560",
    "@openmrs/esm-patient-forms-app": "9.1.1-pre.6560",
    "@openmrs/esm-patient-vitals-app": "9.1.1-pre.6560",
    "@openmrs/esm-patient-immunizations-app": "9.1.1-pre.6560",
    "@openmrs/esm-generic-patient-widgets-app": "9.1.1-pre.6560",
    "@openmrs/esm-patient-orders-app": "9.1.1-pre.6560",
    "@openmrs/esm-patient-notes-app": "9.1.1-pre.6560",
    "@openmrs/esm-patient-attachments-app": "9.1.1-pre.6560",
    "@openmrs/esm-patient-medications-app": "9.1.1-pre.6560",
    "@openmrs/esm-patient-tests-app": "9.1.1-pre.6648",
    "@openmrs/esm-patient-chart-app": "9.1.1-pre.6648",
    "@openmrs/esm-laboratory-app": "1.0.1-pre.467",
    "@openmrs/esm-dispensing-app": "1.6.1-pre.414",
    "@openmrs/esm-ward-app": "8.1.2-pre.4613",
    "@kenyaemr/esm-stock-management-app": "3.0.5-pre.24",
    "@openmrs/esm-active-visits-app": "8.1.1",
    "@kenyaemr/esm-patient-search-app": "8.1.2-pre.165",
    "@kenyaemr/esm-appointments-app": "8.1.2-pre.183",
    "@kenyaemr/esm-service-queues-app": "8.1.2-pre.163",
    "@kenyaemr/esm-patient-registration-app": "8.1.2-pre.165",
    "@kenyaemr/esm-login-app": "latest",
    "@kenyaemr/esm-bed-management-app": "8.1.2-pre.171",
    "@kenyaemr/esm-patient-flags-app": "5.4.1-pre.1936",
    "@kenyaemr/esm-version-app": "5.4.1-pre.1936",
    "@kenyaemr/esm-care-panel-app": "5.4.1-pre.1936",
    "@kenyaemr/esm-billing-app": "5.4.1-pre.1936",
    "@kenyaemr/esm-patient-clinical-view-app": "5.4.1-pre.1936",
    "@kenyaemr/esm-shr-app": "5.4.1-pre.1936",
    "@kenyaemr/esm-providers-app": "5.4.1-pre.1936",
    "@kenyaemr/esm-lab-manifest-app": "5.4.1-pre.1936",
    "@kenyaemr/esm-pharmacy-app": "5.4.1-pre.1936",
    "@kenyaemr/esm-admin-app": "5.4.1-pre.1936",
    "@kenyaemr/esm-imaging-orders-app": "4.0.6-pre.67",
    "@kenyaemr/esm-procedure-orders-app": "4.0.6-pre.67",
    "@kenyaemr/esm-medical-supply-orders-app": "4.0.6-pre.67",
    "@kenyaemr/esm-medical-supply-dispensing-app": "4.0.6-pre.67",
    "@kenyaemr/esm-facility-dashboard-app": "5.4.1-pre.1936"
  },
  "spaPath": "/openmrs/spa",
  "apiUrl": "/openmrs",
  "configUrls": [
    "${openmrsSpaBase}/kenyaemr.config.json",
    "${openmrsSpaBase}/openmrs.config.json"
  ],
  "importmap": "/openmrs/spa/importmap.json"
}
